airslate/__init__.py
airslate/client.py
airslate/exceptions.py
airslate/session.py
airslate/entities/__init__.py
airslate/entities/addons.py
airslate/entities/base.py
airslate/entities/documents.py
airslate/entities/fields.py
airslate/resources/__init__.py
airslate/resources/addons.py
airslate/resources/slate_addon.py
airslate-0.2.1.dist-info/LICENSE
airslate-0.2.1.dist-info/METADATA
airslate-0.2.1.dist-info/WHEEL
airslate-0.2.1.dist-info/top_level.txt
airslate-0.2.1.dist-info/RECORD
