Metadata-Version: 2.1
Name: airslate
Version: 0.2.1
Summary: Official Python client library for the airSlate API v1
Home-page: https://github.com/airslate-oss/python-airslate
Author: airSlate
Author-email: dev-support@airslate.com
Maintainer: airSlate
Maintainer-email: dev-support@airslate.com
License: Apache 2.0
Project-URL: Bug Tracker, https://github.com/airslate-oss/python-airslate/issues
Project-URL: Source Code, https://github.com/airslate-oss/python-airslate
Keywords: airslate,crm,nocode,addons,bots
Platform: any
Classifier: Development Status :: 1 - Planning
Classifier: Environment :: Console
Classifier: Intended Audience :: Developers
Classifier: Natural Language :: English
Classifier: License :: OSI Approved :: Apache Software License
Classifier: Operating System :: OS Independent
Classifier: Programming Language :: Python
Classifier: Programming Language :: Python :: 3
Classifier: Programming Language :: Python :: 3.7
Classifier: Programming Language :: Python :: 3.8
Classifier: Programming Language :: Python :: 3.9
Classifier: Programming Language :: Python :: 3.10
Classifier: Programming Language :: Python :: 3 :: Only
Requires-Python: >=3.7, <4
Requires-Dist: requests (==2.*,>=2.20.0)
Requires-Dist: urllib3 (<1.27,>=1.21.1)
Provides-Extra: testing
Requires-Dist: pytest ; extra == 'testing'
Requires-Dist: responses ; extra == 'testing'
